{
  "decision": "WAIT",
  "target": "NONE",
  "attack_factor": 0.85,
  "rationale": "基于 2026-02-25 11:31 的实时行情数据，数据健康审计显示 macro_health 状态为 SUCCESS，数据时效性极佳。宏观特征引擎显示环境正处于“强力改善”阶段：CNH 汇率 z_score 为 -2.13 且斜率为负，显示人民币强劲升值；A50 期货与融资余额（Margin Debt）均处于 20 日分位的 100% 水平，暗示内资情绪与杠杆资金正加速入场。然而，技术面审计未触发核心逻辑：当前 technical_matrix 中无标的同时满足 Bias < -2.5% 且 Vol Ratio > 1.2 的超跌反转条件。中概互联网 ETF (513050) 乖离率 -2.25% 最为接近，但量比仅 0.56，显示缺乏恐慌盘出清或强力承接；红利 ETF (510880) 量比 1.15 虽活跃，但处于正乖离区间。综上，宏观虽暖但技术面买点未现，故判定为 WAIT。",
  "parameters": {
    "stop_loss": -1.5,
    "stop_profit": 5.0,
    "time_limit": "3天"
  },
  "top_candidates": [
    {
      "code": "513050",
      "name": "中概互联网ETF易方达",
      "reason": "乖离率 -2.25% 最接近触发线，需关注量比是否突破 1.2"
    },
    {
      "code": "510880",
      "name": "红利ETF华泰柏瑞",
      "reason": "量比 1.15 居首，显示资金在防御性板块有活跃迹象"
    }
  ],
  "timestamp": "2026-02-25 11:31",
  "macro_snapshot": {
    "CNH": {
      "value": 6.868,
      "change_pct": -1.09,
      "p_20d": 5.0,
      "p_250d": 0.4,
      "p_1250d": 25.12,
      "z_score": -2.13,
      "slope": -0.003
    },
    "Nasdaq": {
      "value": 24977.044,
      "change_pct": 1.09,
      "p_20d": 75.0,
      "p_250d": 86.0,
      "p_1250d": 97.2,
      "z_score": 0.95,
      "slope": 53.62
    },
    "HangSeng": {
      "value": 26745.2,
      "change_pct": 0.582,
      "p_20d": 25.0,
      "p_250d": 73.6,
      "p_1250d": 90.48,
      "z_score": -1.15,
      "slope": -33.696
    },
    "A50_Futures": {
      "value": 14956.0,
      "change_pct": 1.583,
      "p_20d": 100.0,
      "p_250d": 91.6,
      "p_1250d": 98.32,
      "z_score": 1.87,
      "slope": 53.464
    },
    "VIX": {
      "value": 20.261,
      "change_pct": 0.054,
      "p_20d": 20.0,
      "p_250d": 78.8,
      "p_1250d": 66.56,
      "z_score": -1.46,
      "slope": -0.169
    },
    "Gold": {
      "value": 5206.304,
      "change_pct": 0.58,
      "p_20d": 95.0,
      "p_250d": 98.8,
      "p_1250d": 99.76,
      "z_score": 0.71,
      "slope": 3.037
    },
    "CrudeOil": {
      "value": 66.362,
      "change_pct": 1.115,
      "p_20d": 50.0,
      "p_250d": 85.417,
      "p_1250d": 85.417,
      "z_score": 0.15,
      "slope": 0.011
    },
    "CN10Y": {
      "value": 1.802,
      "change_pct": null,
      "p_20d": 100.0,
      "p_250d": 47.2,
      "p_1250d": 17.52,
      "z_score": 2.0,
      "slope": 0.002
    },
    "US10Y": {
      "value": 4.04,
      "change_pct": null,
      "p_20d": 70.0,
      "p_250d": 16.8,
      "p_1250d": 51.12,
      "z_score": -0.32,
      "slope": 0.002
    },
    "SHIBOR": {
      "value": 1.378,
      "change_pct": null,
      "p_20d": 100.0,
      "p_250d": 79.6,
      "p_1250d": 32.08,
      "z_score": 1.37,
      "slope": 0.003
    },
    "A_Share_Vol": {
      "amplitude": 1.117,
      "pct_change": 1.237,
      "p_20d": 10.0,
      "p_250d": 84.8,
      "p_1250d": 78.476,
      "z_score": -1.65,
      "slope": 8.555
    },
    "Southbound": {
      "value": -12.238,
      "change_pct": null,
      "p_20d": 5.0,
      "p_250d": 9.6,
      "p_1250d": 16.08,
      "z_score": -0.74,
      "slope": -8.647
    },
    "Margin_Debt": {
      "value": 26142.388,
      "change_pct": 1.337,
      "p_20d": 100.0,
      "p_250d": 77.6,
      "p_1250d": 95.52,
      "z_score": 1.28,
      "slope": 68.962
    }
  }
}